eclatdigital_ocean-13.2.1.dist-info/licenses/LICENSE.md
ocean/__init__.py
ocean/__init__.pyi
ocean/abyss.cp313-win_amd64.pyd
ocean/_examples/brewster-polarization.ocxml
ocean/_examples/cornellbox-softconeemitter.ocxml
ocean/_examples/cornellbox.ocxml
ocean/_examples/cube-editmaterials.ocxml
ocean/_examples/flacon-miemedium.ocbinz
ocean/_examples/prism-spectral.ocxml
ocean/_examples/seashell-carpaint.ocxml
ocean/_examples/seashell-glass.ocxml
ocean/_examples/seashell-grinded-steel.ocxml
ocean/_examples/seashell-plasticbump.ocxml
ocean/_examples/seashell-rough-copper.ocxml
ocean/_examples/seashell.ocbinz
ocean/_examples/shapes-editlayers.ocxml
ocean/_examples/shapes-editsetup.ocxml
ocean/_examples/shapes-globalscene.ocxml
ocean/_examples/sphere-lightlayers.ocxml
ocean/_examples/twospheres-metamerism.ocxml
ocean/_examples/twoteapots-volumesurface.ocxml
ocean/abyss/__init__.pyi
ocean/abyss/nodes/__init__.pyi
ocean/abyss/nodes/avspectrum.pyi
ocean/abyss/nodes/bsdf.pyi
ocean/abyss/nodes/colloid.pyi
ocean/abyss/nodes/dielectricfunc.pyi
ocean/abyss/nodes/emitter.pyi
ocean/abyss/nodes/environment.pyi
ocean/abyss/nodes/filter.pyi
ocean/abyss/nodes/filtershader.pyi
ocean/abyss/nodes/geometries.pyi
ocean/abyss/nodes/image.pyi
ocean/abyss/nodes/instrument.pyi
ocean/abyss/nodes/intlaw.pyi
ocean/abyss/nodes/layer.pyi
ocean/abyss/nodes/material.pyi
ocean/abyss/nodes/medium.pyi
ocean/abyss/nodes/normalshader.pyi
ocean/abyss/nodes/output.pyi
ocean/abyss/nodes/roughness.pyi
ocean/abyss/nodes/rtf.pyi
ocean/abyss/nodes/scalarshader.pyi
ocean/abyss/nodes/scattering.pyi
ocean/abyss/nodes/sensor.pyi
ocean/abyss/nodes/setup.pyi
ocean/abyss/nodes/spectrum.pyi
ocean/abyss/nodes/text.pyi
ocean/data/libraries/ocean-building-glass.oclib
ocean/data/libraries/ocean-metals.oclib
ocean/data/libraries/ocean.oclib
ocean/lib/SketchUpAPI.dll
ocean/lib/SketchUpCommonPreferences.dll
ocean/lib/dtkw.dll
ocean/lib/embree3.dll
ocean/lib/libabyss.dll
ocean/lib/libabyssCommon.dll
ocean/lib/libabyssNode.dll
ocean/lib/libgcc_s_seh-1.dll
eclatdigital_ocean-13.2.1.dist-info/METADATA
eclatdigital_ocean-13.2.1.dist-info/WHEEL
eclatdigital_ocean-13.2.1.dist-info/top_level.txt
eclatdigital_ocean-13.2.1.dist-info/RECORD
