Metadata-Version: 2.1
Name: eclatdigital-ocean
Version: 13.2.1
Summary: Python bindings of Ocean™ illumination engine
Home-page: https://eclat-digital.com/software
Author: Eclat-Digital Research
Author-email: pypi@eclat-digital.com
License: Other/Proprietary License
Platform: win-amd64
Classifier: License :: Other/Proprietary License
Classifier: Topic :: Scientific/Engineering :: Physics
Classifier: Topic :: Multimedia :: Graphics :: 3D Rendering
Classifier: Intended Audience :: Science/Research
Classifier: Intended Audience :: Developers
Classifier: Programming Language :: Python :: 3.8
Classifier: Programming Language :: Python :: 3.9
Classifier: Programming Language :: Python :: 3.10
Classifier: Programming Language :: Python :: 3.11
Classifier: Programming Language :: Python :: 3.12
Classifier: Programming Language :: Python :: 3.13
Classifier: Operating System :: POSIX :: Linux
Classifier: Operating System :: Microsoft :: Windows :: Windows 10
Classifier: Operating System :: Microsoft :: Windows :: Windows 11
Requires-Python: >=3.8
License-File: LICENSE.md
Requires-Dist: numpy
Provides-Extra: tuto-deps
Requires-Dist: progressbar; extra == "tuto-deps"
Requires-Dist: trimesh; extra == "tuto-deps"
Requires-Dist: pyrender; extra == "tuto-deps"
Requires-Dist: scipy; extra == "tuto-deps"
Requires-Dist: opencv-python; extra == "tuto-deps"
Requires-Dist: scikit-image; extra == "tuto-deps"
Provides-Extra: utils
Requires-Dist: progressbar; extra == "utils"
Requires-Dist: trimesh; extra == "utils"
Requires-Dist: pyrender; extra == "utils"
